{
  "read_id": "29KF0yeGhp8ZFtqJ",
  "title": "দিনাজপুর বোর্ড ২০২৫",
  "count": 30,
  "questions": [
    {
      "number": "1",
      "tag": "Din B 25",
      "question": "যন্ত্রপাতি ক্রয়ের পরিবহন ব্যয় কোন জাতীয় ব্যয়?",
      "options": [
        {
          "label": "ক",
          "text": "মুনাফাজাতীয় ব্যয়",
          "is_correct": false
        },
        {
          "label": "খ",
          "text": "বিলম্বিত মুনাফাজাতীয় ব্যয়",
          "is_correct": false
        },
        {
          "label": "গ",
          "text": "মূলধনজাতীয় ব্যয়",
          "is_correct": true
        },
        {
          "label": "ঘ",
          "text": "নিয়মিত ব্যয়",
          "is_correct": false
        }
      ],
      "option_a": "মুনাফাজাতীয় ব্যয়",
      "option_b": "বিলম্বিত মুনাফাজাতীয় ব্যয়",
      "option_c": "মূলধনজাতীয় ব্যয়",
      "option_d": "নিয়মিত ব্যয়",
      "correct": "গ",
      "explanation": "যন্ত্রপাতি ক্রয়ের পরিবহন ব্যয় গ মূলধনজাতীয় ব্যয় । ব্যাখ্যা: মূলধনজাতীয় ব্যয়: কোনো স্থায়ী সম্পদ অর্জন বা তার উপযোগিতা বৃদ্ধি করার জন্য যে ব্যয়গুলো করা হয় এবং যার সুবিধা একাধিক বছর ধরে পাওয়া যায়, তাকে মূলধনজাতীয় ব্যয় বলে। যন্ত্রপাতি ব্যবহারের উপযোগী করা পর্যন্ত সকল খরচ, যেমন ক্রয়মূল্য, পরিবহন খরচ, শুল্ক, সংস্থাপন ব্যয় ইত্যাদি যন্ত্রপাতির মূল মূল্যের সাথে যোগ করে মূলধনজাতীয় ব্যয় হিসেবে দেখানো হয়।"
    },
    {
      "number": "2",
      "tag": "Din B 25",
      "question": "শাফি এন্ড ব্রাদার্স একটি একমালিকানা ব্যবসায় প্রতিষ্ঠান। তার প্রারম্ভিক মূলধন, ৯০,০০০ টাকা, বছর শেষে সম্পদ ৮০,০০০ টাকা এবং ব্যাংক ঋণ ৩০,০০০ টাকা, উত্তোলন ২৫,০০০ টাকা, অতিরিক্ত মূলধন। ১৫,০০০ টাকা। সমাপনী মূলধনের পরিমাণ কত?",
      "options": [
        {
          "label": "ক",
          "text": "৮০,০০০ টাকা",
          "is_correct": false
        },
        {
          "label": "খ",
          "text": "৭০,০০০ টাকা",
          "is_correct": false
        },
        {
          "label": "গ",
          "text": "৬০,০০০ টাকা",
          "is_correct": false
        },
        {
          "label": "ঘ",
          "text": "৫০,০০০ টাকা",
          "is_correct": true
        }
      ],
      "option_a": "৮০,০০০ টাকা",
      "option_b": "৭০,০০০ টাকা",
      "option_c": "৬০,০০০ টাকা",
      "option_d": "৫০,০০০ টাকা",
      "correct": "ঘ",
      "explanation": "সমাপনী মূলধন = সমাপনী সম্পদ- সমাপনী দায় = ৮০,০০০- ৩০,০০০ = ৫০,০০০ টাকা।"
    },
    {
      "number": "3",
      "tag": "Din B 25",
      "question": "শাফি এন্ড ব্রাদার্স একটি একমালিকানা ব্যবসায় প্রতিষ্ঠান। তার প্রারম্ভিক মূলধন, ৯০,০০০ টাকা, বছর শেষে সম্পদ ৮০,০০০ টাকা এবং ব্যাংক ঋণ ৩০,০০০ টাকা, উত্তোলন ২৫,০০০ টাকা, অতিরিক্ত মূলধন। ১৫,০০০ টাকা। মুনাফা/ক্ষতির পরিমাণ কত?",
      "options": [
        {
          "label": "ক",
          "text": "মুনাফা ৩০,০০০ টাকা",
          "is_correct": false
        },
        {
          "label": "খ",
          "text": "ক্ষতি ৩০,০০০ টাকা",
          "is_correct": true
        },
        {
          "label": "গ",
          "text": "মুনাফা ৩৫,০০০ টাকা",
          "is_correct": false
        },
        {
          "label": "ঘ",
          "text": "ক্ষতি ৩৫,০০০ টাকা",
          "is_correct": false
        }
      ],
      "option_a": "মুনাফা ৩০,০০০ টাকা",
      "option_b": "ক্ষতি ৩০,০০০ টাকা",
      "option_c": "মুনাফা ৩৫,০০০ টাকা",
      "option_d": "ক্ষতি ৩৫,০০০ টাকা",
      "correct": "খ",
      "explanation": "মুনাফা/ক্ষতি = {(সমাপনী মূলধন + উত্তোলন)- (প্রারম্ভিক মূলধন +অতিরিক্ত মূলধন)) = (৫০,০০০ + ২৫,০০০) - (৯০,০০০ + ১৫,০০০) .. ক্ষতি = ৩০,০০০ টাকা।"
    },
    {
      "number": "4",
      "tag": "Din B 25",
      "question": "উপর্যুক্ত ছকটি কোন ধরনের ছক?",
      "options": [
        {
          "label": "ক",
          "text": "T ছক",
          "is_correct": false
        },
        {
          "label": "খ",
          "text": "সনাতনী ছক",
          "is_correct": false
        },
        {
          "label": "গ",
          "text": "জাবেদা ছক",
          "is_correct": false
        },
        {
          "label": "ঘ",
          "text": "চলমান জের ছক",
          "is_correct": true
        }
      ],
      "option_a": "T ছক",
      "option_b": "সনাতনী ছক",
      "option_c": "জাবেদা ছক",
      "option_d": "চলমান জের ছক",
      "correct": "ঘ",
      "explanation": "উপর্যুক্ত ছকটি চলমান জের ছক"
    },
    {
      "number": "5",
      "tag": "Din B 25",
      "question": "দেনাদারের মৃত্যু বা দেউলিয়ার কারণে অর্থ আদায় অসম্ভব হলে কোন ধরনের হিসাব খোলা হয়?",
      "options": [
        {
          "label": "ক",
          "text": "কুঋণ হিসাব",
          "is_correct": true
        },
        {
          "label": "খ",
          "text": "প্রাপ্য হিসাব",
          "is_correct": false
        },
        {
          "label": "গ",
          "text": "প্রদেয় হিসাব",
          "is_correct": false
        },
        {
          "label": "ঘ",
          "text": "ঋণ হিসাব",
          "is_correct": false
        }
      ],
      "option_a": "কুঋণ হিসাব",
      "option_b": "প্রাপ্য হিসাব",
      "option_c": "প্রদেয় হিসাব",
      "option_d": "ঋণ হিসাব",
      "correct": "ক",
      "explanation": "দেনাদারের মৃত্যু বা দেউলিয়ার কারণে অর্থ আদায় অসম্ভব হলে ক কুঋণ হিসাব খোলা হয়। ব্যাখ্যা কুঋণ (Bad Debts): যখন কোনো দেনাদারের কাছ থেকে আইনগতভাবে বা অন্য কোনো কারণে পাওনা টাকা আদায় করা সম্ভব হয় না, তখন সেই অনাদায়ী পাওনা টাকাকে কুঋণ বা অনাদায়ী পাওনা বলা হয়। এটি ব্যবসা প্রতিষ্ঠানের জন্য একটি পরিচালন ব্যয় বা ক্ষতি। অন্যান্য বিকল্পগুলো হলো: প্রাপ্য হিসাব: এটি দেনাদারের অপর নাম। প্রদেয় হিসাব: এটি পাওনাদারের অপর নাম (যাকে টাকা দিতে হবে)। ঋণ হিসাব: এটি সাধারণত ব্যাংক বা অন্য কোনো উৎস থেকে নেওয়া বড় অঙ্কের ঋণকে বোঝায়।"
    },
    {
      "number": "6",
      "tag": "Din B 25",
      "question": "পেনসিল ক্রয় কোন ধরনের হিসাবে অন্তর্ভুক্ত হবে?",
      "options": [
        {
          "label": "ক",
          "text": "ক্রয় হিসাব",
          "is_correct": false
        },
        {
          "label": "খ",
          "text": "মনিহারি হিসাব",
          "is_correct": true
        },
        {
          "label": "গ",
          "text": "অফিস সাপ্লাই হিসাব",
          "is_correct": false
        },
        {
          "label": "ঘ",
          "text": "অফিস সরঞ্জাম হিসাব",
          "is_correct": false
        }
      ],
      "option_a": "ক্রয় হিসাব",
      "option_b": "মনিহারি হিসাব",
      "option_c": "অফিস সাপ্লাই হিসাব",
      "option_d": "অফিস সরঞ্জাম হিসাব",
      "correct": "খ",
      "explanation": "পেনসিল ক্রয় খ মনিহারি হিসাব -এ অন্তর্ভুক্ত হবে। ব্যাখ্যা ব্যবসায় প্রতিষ্ঠানে ব্যবহৃত ছোট ও স্বল্পমূল্যের জিনিসপত্র, যেমন: পেনসিল, কলম, কাগজ, স্ট্যাপলার পিন ইত্যাদি মনিহারি (Stationery) হিসেবে গণ্য করা হয়। এটি একটি মুনাফাজাতীয় ব্যয়। ক ক্রয় হিসাব : এটি শুধুমাত্র পুনবিক্রয়ের উদ্দেশ্যে পণ্য ক্রয়ের জন্য ব্যবহৃত হয়। গ অফিস সাপ্লাই হিসাব : এটিও মনিহারির সমার্থক শব্দ, তবে বাংলাভাষী অ্যাকাউন্টিং সিস্টেমে \"মনিহারি হিসাব\" শব্দটিই বেশি প্রচলিত। ঘ অফিস সরঞ্জাম হিসাব : এটি দীর্ঘমেয়াদী ও দামী সম্পদের জন্য ব্যবহৃত হয় (যেমন: কম্পিউটার, ফটোকপি মেশিন)।"
    },
    {
      "number": "7",
      "tag": "Din B 25",
      "question": "প্রচারের জন্য পণ্য বিতরণ এক্ষেত্রে কোন হিসাবটি ক্রেডিট হবে?",
      "options": [
        {
          "label": "ক",
          "text": "পণ্য হিসাব",
          "is_correct": false
        },
        {
          "label": "খ",
          "text": "বিজ্ঞাপন হিসাব",
          "is_correct": false
        },
        {
          "label": "গ",
          "text": "ক্রয় হিসাব",
          "is_correct": true
        },
        {
          "label": "ঘ",
          "text": "বিতরণ হিসাব",
          "is_correct": false
        }
      ],
      "option_a": "পণ্য হিসাব",
      "option_b": "বিজ্ঞাপন হিসাব",
      "option_c": "ক্রয় হিসাব",
      "option_d": "বিতরণ হিসাব",
      "correct": "গ",
      "explanation": "প্রচারের জন্য পণ্য বিতরণ করা হলে এক্ষেত্রে গ ক্রয় হিসাব ক্রেডিট হবে। ব্যাখ্যা বিজ্ঞাপন হিসাব ডেবিট: পণ্য বিতরণের মাধ্যমে বিজ্ঞাপন (Advertising) বাবদ খরচ হয়। খরচ বৃদ্ধি পেলে বিজ্ঞাপন হিসাবকে ডেবিট করা হয়। ক্রয় হিসাব ক্রেডিট: যখন পণ্য বিক্রয় ছাড়া অন্য কোনো উদ্দেশ্যে (যেমন: বিজ্ঞাপন, চুরি, উত্তোলন, বিনামূল্যে বিতরণ) ব্যবসা প্রতিষ্ঠান থেকে পণ্য চলে যায়, তখন মজুদ পণ্যের পরিমাণ কমে যায়। হিসাববিজ্ঞানে পণ্যের মজুদ কমানোর জন্য ক্রয় হিসাবকে ক্রেডিট করা হয়।"
    },
    {
      "number": "8",
      "tag": "Din B 25",
      "question": "ক্রয় জাবেদার উৎস দলিল কোনটি?",
      "options": [
        {
          "label": "ক",
          "text": "চালান",
          "is_correct": true
        },
        {
          "label": "খ",
          "text": "ভাউচার",
          "is_correct": false
        },
        {
          "label": "গ",
          "text": "ডেবিট নোট",
          "is_correct": false
        },
        {
          "label": "ঘ",
          "text": "ক্রেডিট নোট",
          "is_correct": false
        }
      ],
      "option_a": "চালান",
      "option_b": "ভাউচার",
      "option_c": "ডেবিট নোট",
      "option_d": "ক্রেডিট নোট",
      "correct": "ক",
      "explanation": "ক্রয় জাবেদা (Purchase Journal) হলো সেই বই যেখানে শুধুমাত্র ধারে বা বাকিতে পণ্য ক্রয় লিপিবদ্ধ করা হয়। ধারে পণ্য ক্রয়ের সময় বিক্রেতা ক্রেতাকে যে বাণিজ্যিক দলিলটি দেয়, সেটি হলো চালান (Invoice)। চালান হলো লেনদেনের একটি প্রাথমিক প্রমাণপত্র বা উৎস দলিল। এই চালানের ভিত্তিতেই ক্রয় জাবেদায় লেনদেনটি লেখা হয়। খ ভাউচার: এটি নগদ লেনদেনের (নগদ প্রদান বা গ্রহণ) উৎস দলিল। গ ডেবিট নোট: এটি ক্রয় ফেরতের উৎস দলিল। ঘ ক্রেডিট নোট: এটি বিক্রয় ফেরতের উৎস দলিল। সঠিক উত্তর: ক চালান"
    },
    {
      "number": "9",
      "tag": "Din B 25",
      "question": "ধারে সম্পত্তি ক্রয়-বিক্রয় কোন জাবেদায় লিপিবন্ধ হবে?",
      "options": [
        {
          "label": "ক",
          "text": "বিক্রয় জাবেদা",
          "is_correct": false
        },
        {
          "label": "খ",
          "text": "নগদ প্রদান জাবেদা",
          "is_correct": false
        },
        {
          "label": "গ",
          "text": "অন্যান্য জাবেদা",
          "is_correct": true
        },
        {
          "label": "ঘ",
          "text": "ক্রয় জাবেদা",
          "is_correct": false
        }
      ],
      "option_a": "বিক্রয় জাবেদা",
      "option_b": "নগদ প্রদান জাবেদা",
      "option_c": "অন্যান্য জাবেদা",
      "option_d": "ক্রয় জাবেদা",
      "correct": "গ",
      "explanation": "সঠিক অপশন হলো গ. অন্যান্য জাবেদা । ব্যাখ্যা নির্দিষ্ট ধরনের লেনদেনের জন্য বিশেষ জাবেদা বই ব্যবহার করা হয় (যেমন: নগদ ক্রয়-বিক্রয়ের জন্য নগদ জাবেদা, ধারে পণ্য ক্রয়-বিক্রয়ের জন্য ক্রয়/বিক্রয় জাবেদা)। ধারে সম্পত্তি ক্রয়-বিক্রয় (যেমন: ধারে আসবাবপত্র বা যন্ত্রপাতি ক্রয়/বিক্রয়) হলো অনিয়মিত প্রকৃতির লেনদেন। এটি পণ্য নয়, বরং স্থায়ী সম্পত্তি। যে সমস্ত লেনদেন বিশেষ জাবেদা বইগুলোতে লেখা হয় না, সেগুলো সাধারণ জাবেদা (General Journal) বা অন্যান্য জাবেদা বইতে লিপিবদ্ধ করা হয়।"
    },
    {
      "number": "10",
      "tag": "Din B 25",
      "question": "জনাব নাফি বিক্রয় বৃদ্ধির জন্য পূর্ব নির্ধারিত বিক্রয়মূল্য অপেক্ষা কমমূল্যে পণ্য বিক্রয় করে থাকেন এক্ষেত্রে তিনি কোন ধরনের ছাড় দেন?",
      "options": [
        {
          "label": "ক",
          "text": "নগদ বাট্টা",
          "is_correct": false
        },
        {
          "label": "খ",
          "text": "প্রদত্ত বাট্টা",
          "is_correct": false
        },
        {
          "label": "গ",
          "text": "প্রাপ্ত বাট্টা",
          "is_correct": false
        },
        {
          "label": "ঘ",
          "text": "কারবারি বাট্টা",
          "is_correct": true
        }
      ],
      "option_a": "নগদ বাট্টা",
      "option_b": "প্রদত্ত বাট্টা",
      "option_c": "প্রাপ্ত বাট্টা",
      "option_d": "কারবারি বাট্টা",
      "correct": "ঘ",
      "explanation": "জনাব নাফি বিক্রয় বৃদ্ধির জন্য পূর্ব নির্ধারিত বিক্রয়মূল্য অপেক্ষা কমমূল্যে পণ্য বিক্রয় করে থাকলে তিনি ঘ) কারবারি বাট্টা (Trade Discount) দেন। ব্যাখ্যা: কারবারি বাট্টা: পণ্য বিক্রয় বৃদ্ধির উদ্দেশ্যে বা দ্রুত পণ্য বিক্রয়ের জন্য পণ্যের তালিকা মূল্য বা পূর্ব নির্ধারিত মূল্য থেকে যে পরিমাণ অর্থ ছাড় দেওয়া হয়, তাকে কারবারি বাট্টা বলে। এই বাট্টা সাধারণত চালান তৈরির সময়ই বাদ দেওয়া হয় এবং হিসাবের বইয়ে আলাদাভাবে লিপিবদ্ধ করা হয় না। নগদ বাট্টা/প্রদত্ত বাট্টা: এটি সাধারণত বাকিতে বিক্রিত পণ্যের টাকা দ্রুত আদায়ের জন্য দেনাদারকে দেওয়া হয় এবং এটি হিসাবের বইয়ে (নগদান বইয়ে) লিপিবদ্ধ করা হয়। এই প্রশ্নটি বিক্রয় বৃদ্ধির উদ্দেশ্যে মূল্য কমানোর কথা বলছে, টাকা আদায়ের জন্য নয়।"
    },
    {
      "number": "11",
      "tag": "Din B 25",
      "question": "সহকারী খতিয়ান- i. ক্রয় হিসাব ii. তামিম এন্টারপ্রাইজ iii. মীম ট্রেডার্স নিচের কোনটি সঠিক?",
      "options": [
        {
          "label": "ক",
          "text": "i ও ii",
          "is_correct": false
        },
        {
          "label": "খ",
          "text": "i ও iii",
          "is_correct": false
        },
        {
          "label": "গ",
          "text": "ii ও iii",
          "is_correct": true
        },
        {
          "label": "ঘ",
          "text": "i, ii ও iii",
          "is_correct": false
        }
      ],
      "option_a": "i ও ii",
      "option_b": "i ও iii",
      "option_c": "ii ও iii",
      "option_d": "i, ii ও iii",
      "correct": "গ",
      "explanation": "সঠিক উত্তর হলো গ ii ও iii । ব্যাখ্যা: সহকারী খতিয়ান (Subsidiary Ledger): সহকারী খতিয়ান হলো মূল খতিয়ানের (General Ledger) বিস্তারিত বিবরণ। সাধারণত দেনাদার (Accounts Receivable) এবং পাওনাদারদের (Accounts Payable) প্রত্যেকের জন্য আলাদা আলাদা হিসাব সংরক্ষণের জন্য সহকারী খতিয়ান ব্যবহার করা হয়, যাতে নির্দিষ্ট ব্যক্তি বা প্রতিষ্ঠানের কাছে কত টাকা পাওনা বা দেনা আছে তা সহজে জানা যায়। তামিম এন্টারপ্রাইজ এবং মীম ট্রেডার্স হলো নির্দিষ্ট পাওনাদার বা দেনাদার প্রতিষ্ঠানের নাম, তাই এদের হিসাবগুলো সহকারী খতিয়ানের অংশ হবে। ক্রয় হিসাব (Purchases Account): এটি একটি মূল খতিয়ান (General Ledger) বা নিয়ন্ত্রণ হিসাব (Control Account), সহকারী খতিয়ান নয়। সহকারী খতিয়ানের মোট যোগফল মূল খতিয়ানের ক্রয় বা বিক্রয় নিয়ন্ত্রণ হিসাবের সাথে মিলানো হয়।"
    },
    {
      "number": "12",
      "tag": "Din B 25",
      "question": "উপযুক্ত তথ্য হতে ব্যাংক হিসাবের উদ্বৃত্ত কত?",
      "options": [
        {
          "label": "ক",
          "text": "ডেবিট উদ্বৃত্ত ১৫,০০০ টাকা",
          "is_correct": true
        },
        {
          "label": "খ",
          "text": "ক্রেডিট উদ্বৃত্ত ১৫,০০০ টাকা",
          "is_correct": false
        },
        {
          "label": "গ",
          "text": "ডেবিট উদ্বৃত্ত ২০,০০০ টাকা",
          "is_correct": false
        },
        {
          "label": "ঘ",
          "text": "ক্রেডিট উদ্বৃত্ত ২৫,০০০ টাকা",
          "is_correct": false
        }
      ],
      "option_a": "ডেবিট উদ্বৃত্ত ১৫,০০০ টাকা",
      "option_b": "ক্রেডিট উদ্বৃত্ত ১৫,০০০ টাকা",
      "option_c": "ডেবিট উদ্বৃত্ত ২০,০০০ টাকা",
      "option_d": "ক্রেডিট উদ্বৃত্ত ২৫,০০০ টাকা",
      "correct": "ক",
      "explanation": ""
    },
    {
      "number": "13",
      "tag": "Din B 25",
      "question": "সাধারণ খতিয়ানে পোস্টিং দেয়া হয়- i. দিনান্তে ii. সপ্তাহান্তে iii. মাসান্তে নিচের কোনটি সঠিক?",
      "options": [
        {
          "label": "ক",
          "text": "i ও ii",
          "is_correct": false
        },
        {
          "label": "খ",
          "text": "i ও iii",
          "is_correct": false
        },
        {
          "label": "গ",
          "text": "ii ও iii",
          "is_correct": false
        },
        {
          "label": "ঘ",
          "text": "i, ii ও iii",
          "is_correct": true
        }
      ],
      "option_a": "i ও ii",
      "option_b": "i ও iii",
      "option_c": "ii ও iii",
      "option_d": "i, ii ও iii",
      "correct": "ঘ",
      "explanation": "সাধারণ খতিয়ানে (General Ledger) পোস্টিং দেওয়া হয়— প্রতিদিনের লেনদেন শেষে (দিনান্তে) সপ্তাহ শেষে (সপ্তাহান্তে) মাস শেষে (মাসান্তে) অর্থাৎ, পোস্টিং সময়ভেদে যেকোনোটিই হতে পারে , প্রতিষ্ঠানের নীতির ওপর নির্ভর করে। সুতরাং সবগুলোই সঠিক। ঘ) i, ii ও iii"
    },
    {
      "number": "14",
      "tag": "Din B 25",
      "question": "রেওয়ামিলে যে সমস্ত ভুল ধরা পড়ে- i. নীতিগত ভুল ii. লেখার ভুল iii. টাকার অঙ্কের ভুল নিচের কোনটি সঠিক?",
      "options": [
        {
          "label": "ক",
          "text": "i ও ii",
          "is_correct": false
        },
        {
          "label": "খ",
          "text": "i ও iii",
          "is_correct": false
        },
        {
          "label": "গ",
          "text": "ii ও iii",
          "is_correct": true
        },
        {
          "label": "ঘ",
          "text": "i, ii ও iii",
          "is_correct": false
        }
      ],
      "option_a": "i ও ii",
      "option_b": "i ও iii",
      "option_c": "ii ও iii",
      "option_d": "i, ii ও iii",
      "correct": "গ",
      "explanation": "রেওয়ামিল (Trial Balance) প্রস্তুত করার মূল উদ্দেশ্য হলো খতিয়ানের ডেবিট ও ক্রেডিট দিকের গাণিতিক নির্ভুলতা যাচাই করা। যেসব ভুল রেওয়ামিলের দুই পাশের যোগফলকে প্রভাবিত করে, শুধুমাত্র সেই ভুলগুলোই রেওয়ামিলে ধরা পড়ে বা রেওয়ামিল মেলানোর মাধ্যমে চিহ্নিত করা যায়। দেওয়া ভুলগুলোর ধরন বিশ্লেষণ করা যাক: i. নীতিগত ভুল: এটি এমন ভুল যা হিসাববিজ্ঞানের মূলনীতি লঙ্ঘন করে (যেমন, সম্পদকে ব্যয় হিসাবে লেখা)। এই ভুলগুলো ডেবিট ও ক্রেডিট উভয় দিকেই সমান অঙ্কের টাকা দিয়ে লেখা হয়, তাই রেওয়ামিলের দুই পাশ মিলে যায় এবং এই ভুল ধরা পড়ে না। ii. লেখার ভুল: খতিয়ানে লেখার সময় টাকার অঙ্কে ভুল হলে (যেমন, ৫০০ টাকার বদলে ৫০ টাকা লেখা), ডেবিট ও ক্রেডিটের পার্থক্য তৈরি হয়, ফলে এই ভুল রেওয়ামিলে ধরা পড়ে। iii. টাকার অঙ্কের ভুল (বাদ পড়ার ভুল/ আংশিক বাদ পড়ার ভুল): যখন কোনো একটি হিসাবের দিকে টাকা লেখা বাদ পড়ে যায় বা ভুল অঙ্ক লেখা হয়, তখন দুই পাশের যোগফল মেলে না, ফলে এই ভুল ধরা পড়ে। সুতরাং, শুধুমাত্র ii এবং iii নং ভুলগুলোই রেওয়ামিলে ধরা পড়ে।"
    },
    {
      "number": "15",
      "tag": "Din B 25",
      "question": "রেওয়ামিলে একটি হিসাবের ক্রেডিট জের ৫০০ টাকা, ভুলে রেওয়ামিলের ডেবিট কলামে লেখা হয়। বাকি উদ্বৃত্তগুলো ঠিক থাকলে রেওয়ামিলের উভয় পার্শ্বের পার্থক্য কত হবে?",
      "options": [
        {
          "label": "ক",
          "text": "২৫০ টাকা",
          "is_correct": false
        },
        {
          "label": "খ",
          "text": "৫০০ টাকা",
          "is_correct": false
        },
        {
          "label": "গ",
          "text": "৭৫০ টাকা",
          "is_correct": false
        },
        {
          "label": "ঘ",
          "text": "১,০০০ টাকা",
          "is_correct": true
        }
      ],
      "option_a": "২৫০ টাকা",
      "option_b": "৫০০ টাকা",
      "option_c": "৭৫০ টাকা",
      "option_d": "১,০০০ টাকা",
      "correct": "ঘ",
      "explanation": "রেওয়ামিলে একটি হিসাবের ক্রেডিট জের ৫০০ টাকা ভুলে ডেবিট কলামে লেখা হলে রেওয়ামিলের উভয় পার্শ্বের পার্থক্য ঘ ১,০০০ টাকা হবে। ব্যাখ্যা: সঠিকভাবে লেখা হলে, ক্রেডিট দিকে ৫০০ টাকা থাকত। ভুলবশত ডেবিট দিকে ৫০০ টাকা লেখা হয়েছে। এর ফলে, রেওয়ামিলের ডেবিট দিকের যোগফল প্রকৃত যোগফলের চেয়ে ৫০০ টাকা বেড়ে গেছে এবং ক্রেডিট দিকের যোগফল প্রকৃত যোগফলের চেয়ে ৫০০ টাকা কমে গেছে (কারণ ৫০০ টাকা ক্রেডিট দিকে লেখা হয়নি)। উভয় দিকের পার্থক্য হবে: ৫০০ টাকা (ডেবিট দিকের অতিরিক্ত) + ৫০০ টাকা (ক্রেডিট দিকের ঘাটতি) = ১,০০০ টাকা ।"
    },
    {
      "number": "16",
      "tag": "Din B 25",
      "question": "কোন হিসাবটি ব্যতিক্রম?",
      "options": [
        {
          "label": "ক",
          "text": "পাওনাদার",
          "is_correct": false
        },
        {
          "label": "খ",
          "text": "প্রদত্ত ঋণ",
          "is_correct": true
        },
        {
          "label": "গ",
          "text": "ঋণ",
          "is_correct": false
        },
        {
          "label": "ঘ",
          "text": "বকেয়া বেতন",
          "is_correct": false
        }
      ],
      "option_a": "পাওনাদার",
      "option_b": "প্রদত্ত ঋণ",
      "option_c": "ঋণ",
      "option_d": "বকেয়া বেতন",
      "correct": "খ",
      "explanation": "এই চারটি হিসাবের মধ্যে খ প্রদত্ত ঋণ হিসাবটি ব্যতিক্রম। ব্যাখ্যা: হিসাববিজ্ঞানের দৃষ্টিকোণ থেকে: ক পাওনাদার , গ ঋণ (গৃহীত ঋণ), এবং ঘ বকেয়া বেতন — এই সবগুলোই হল দায় (Liabilities) । এগুলো ব্যবসা প্রতিষ্ঠানের আর্থিক বাধ্যবাধকতা নির্দেশ করে, অর্থাৎ ভবিষ্যতে কোনো পক্ষকে অর্থ পরিশোধ করতে হবে। খ প্রদত্ত ঋণ — এটি ব্যবসা প্রতিষ্ঠানের একটি সম্পদ (Asset) । যখন প্রতিষ্ঠান অন্য কোনো পক্ষকে ঋণ দেয়, তখন সেই অর্থ ভবিষ্যতে ফেরত পাওয়ার অধিকার জন্মায়। সুতরাং, প্রদত্ত ঋণ হলো একমাত্র সম্পদ হিসাব, বাকিগুলো সবই দায় হিসাব।"
    },
    {
      "number": "17",
      "tag": "Din B 25",
      "question": "হামিম ট্রেডার্স এর নিট বিক্রয় ২১,০০০/=, মোট মুনাফা ১০,০০০/= পরিচালন ক্ষতি ১২,০০০/= । হামিম ট্রেডার্স এর বিক্রীত পণ্যের ব্যয়ের পরিমাণ নির্ণয় কর।",
      "options": [
        {
          "label": "ক",
          "text": "১১,০০০/=",
          "is_correct": true
        },
        {
          "label": "খ",
          "text": "২১,০০০/=",
          "is_correct": false
        },
        {
          "label": "গ",
          "text": "৩১,০০০/=",
          "is_correct": false
        },
        {
          "label": "ঘ",
          "text": "৩৩,০০০/=",
          "is_correct": false
        }
      ],
      "option_a": "১১,০০০/=",
      "option_b": "২১,০০০/=",
      "option_c": "৩১,০০০/=",
      "option_d": "৩৩,০০০/=",
      "correct": "ক",
      "explanation": "বিক্রীত পণ্যের ব্যয় = নিট বিক্রয় – মোট মুনাফা = ২১,০০০ – ১০,০০০ = ১১,০০০ টাকা।"
    },
    {
      "number": "18",
      "tag": "Din B 25",
      "question": "হামিম ট্রেডার্স এর নিট বিক্রয় ২১,০০০/=, মোট মুনাফা ১০,০০০/= পরিচালন ক্ষতি ১২,০০০/= । হামিম ট্রেডার্স এর নিট মুনাফা/ক্ষতির পরিমাণ কত?",
      "options": [
        {
          "label": "ক",
          "text": "নিট মুনাফা ২,০০০/=",
          "is_correct": false
        },
        {
          "label": "খ",
          "text": "নিট ক্ষতি ২,০০০/=",
          "is_correct": true
        },
        {
          "label": "গ",
          "text": "নিট মুনাফা ৯,০০০/=",
          "is_correct": false
        },
        {
          "label": "ঘ",
          "text": "নিট ক্ষতি ৯,০০০/=",
          "is_correct": false
        }
      ],
      "option_a": "নিট মুনাফা ২,০০০/=",
      "option_b": "নিট ক্ষতি ২,০০০/=",
      "option_c": "নিট মুনাফা ৯,০০০/=",
      "option_d": "নিট ক্ষতি ৯,০০০/=",
      "correct": "খ",
      "explanation": "নিট মুনাফা/ক্ষতি = মোট মুনাফা – পরিচালন ক্ষতি = ১০,০০০ – ১২,০০০ ∴ নিট ক্ষতি = ২,০০০ টাকা।"
    },
    {
      "number": "19",
      "tag": "Din B 25",
      "question": "রেওয়ামিলে দেয়া আছে বেতন (৮ মাস)= ৪৮,০০০ টাকা। এক্ষেত্রে বকেয়া বেতনের পরিমাণ কত?",
      "options": [
        {
          "label": "ক",
          "text": "২৪,০০০ টাকা",
          "is_correct": true
        },
        {
          "label": "খ",
          "text": "৩৬,০০০ টাকা",
          "is_correct": false
        },
        {
          "label": "গ",
          "text": "৪২,০০০ টাকা",
          "is_correct": false
        },
        {
          "label": "ঘ",
          "text": "৭২,০০০ টাকা",
          "is_correct": false
        }
      ],
      "option_a": "২৪,০০০ টাকা",
      "option_b": "৩৬,০০০ টাকা",
      "option_c": "৪২,০০০ টাকা",
      "option_d": "৭২,০০০ টাকা",
      "correct": "ক",
      "explanation": "বকেয়া বেতন = প্রদত্ত বেতন × ৪ ৮ \\times \\frac{৪}{৮} × ৮ ৪ ​ = ৪৮,০০০ × ৪ ৮ \\times \\frac{৪}{৮} × ৮ ৪ ​ = ২৪,০০০ টাকা।"
    },
    {
      "number": "20",
      "tag": "Din B 25",
      "question": "মুনাফাজাতীয় ব্যয় কোনটি?",
      "options": [
        {
          "label": "ক",
          "text": "জমি ক্রয়",
          "is_correct": false
        },
        {
          "label": "খ",
          "text": "আসবাবপত্র ক্রয়",
          "is_correct": false
        },
        {
          "label": "গ",
          "text": "যন্ত্রপাতি ক্রয়",
          "is_correct": false
        },
        {
          "label": "ঘ",
          "text": "পণ্য ক্রয়",
          "is_correct": true
        }
      ],
      "option_a": "জমি ক্রয়",
      "option_b": "আসবাবপত্র ক্রয়",
      "option_c": "যন্ত্রপাতি ক্রয়",
      "option_d": "পণ্য ক্রয়",
      "correct": "ঘ",
      "explanation": "মুনাফাজাতীয় ব্যয় হলো ঘ পণ্য ক্রয় ।  ব্যাখ্যা: মুনাফাজাতীয় ব্যয়: যে সব ব্যয় প্রতিষ্ঠানের দৈনন্দিন কার্যক্রম পরিচালনার জন্য নিয়মিতভাবে করা হয় এবং যার উপযোগিতা এক বছরের মধ্যেই শেষ হয়ে যায়, সেগুলোকে মুনাফাজাতীয় ব্যয় বলা হয়। পণ্য ক্রয়: এটি একটি নিয়মিত ও পুনরাবৃত্তিমূলক ব্যয়, যা ব্যবসার মূল কার্যক্রমের জন্য অপরিহার্য। তাই এটি একটি মুনাফাজাতীয় ব্যয়। মূলধনজাতীয় ব্যয়: জমি ক্রয়, আসবাবপত্র ক্রয় এবং যন্ত্রপাতি ক্রয় হলো মূলধনজাতীয় ব্যয়। এই ব্যয়গুলো নিয়মিত হয় না এবং এর থেকে দীর্ঘমেয়াদি সুবিধা পাওয়া যায়।"
    },
    {
      "number": "21",
      "tag": "Din B 25",
      "question": "নগদ প্রদান জাবেদার ছকে কোনটি থাকে?",
      "options": [
        {
          "label": "ক",
          "text": "দেনাদার ক্রেডিট",
          "is_correct": false
        },
        {
          "label": "খ",
          "text": "বিক্রয় ক্রেডিট",
          "is_correct": false
        },
        {
          "label": "গ",
          "text": "নগদ ক্রেডিট",
          "is_correct": true
        },
        {
          "label": "ঘ",
          "text": "অন্যান্য হিসাব ক্রেডিট",
          "is_correct": false
        }
      ],
      "option_a": "দেনাদার ক্রেডিট",
      "option_b": "বিক্রয় ক্রেডিট",
      "option_c": "নগদ ক্রেডিট",
      "option_d": "অন্যান্য হিসাব ক্রেডিট",
      "correct": "গ",
      "explanation": "নগদ প্রদান জাবেদায় সব সময় একটি বিষয় থাকে— নগদ ক্রেডিট (Cash Credit) কারণ: নগদ প্রদান জাবেদা (Cash Payment Journal) হলো এমন জাবেদা যেখানে প্রতিষ্ঠানের নগদ বের হয় , অর্থাৎ নগদ কমে যায় । হিসাববিজ্ঞানে নগদ কমলে নগদ হিসাব ক্রেডিট করা হয়। সুতরাং সঠিক উত্তর: গ) নগদ ক্রেডিট"
    },
    {
      "number": "22",
      "tag": "Din B 25",
      "question": "পারিবারিক বাজেটে শিক্ষা খাতে আনুমানিক ব্যয় শতকরা কত ধরা হয়?",
      "options": [
        {
          "label": "ক",
          "text": "৩০%-৪০%",
          "is_correct": false
        },
        {
          "label": "খ",
          "text": "২০%-২৫%",
          "is_correct": false
        },
        {
          "label": "গ",
          "text": "১৫% ২০%",
          "is_correct": false
        },
        {
          "label": "ঘ",
          "text": "১০%-১৫%",
          "is_correct": true
        }
      ],
      "option_a": "৩০%-৪০%",
      "option_b": "২০%-২৫%",
      "option_c": "১৫% ২০%",
      "option_d": "১০%-১৫%",
      "correct": "ঘ",
      "explanation": "পারিবারিক বাজেটে শিক্ষা খাতে আনুমানিক ব্যয় সাধারণত ঘ ১০%-১৫% ধরা হয়। ব্যাখ্যা আদর্শ পারিবারিক বাজেট প্রণয়নের ক্ষেত্রে সাধারণত নির্দিষ্ট খাত অনুযায়ী ব্যয়ের একটি নির্দেশিকা অনুসরণ করা হয়। যদিও এটি পরিবারের আয় ও অবস্থানের ওপর নির্ভরশীল, তবে শিক্ষাকে একটি গুরুত্বপূর্ণ খাত হিসেবে বিবেচনা করে ব্যয়ের এই সীমা নির্ধারণ করা হয়।"
    },
    {
      "number": "23",
      "tag": "Din B 25",
      "question": "দরপত্রের ক্রয়মূল্য কোন ধরনের খরচ?",
      "options": [
        {
          "label": "ক",
          "text": "অফিস খরচ",
          "is_correct": false
        },
        {
          "label": "খ",
          "text": "প্রশাসনিক",
          "is_correct": false
        },
        {
          "label": "গ",
          "text": "বিক্রয়",
          "is_correct": false
        },
        {
          "label": "ঘ",
          "text": "আরোপণ যোগ্য (প্রত্যক্ষ)",
          "is_correct": true
        }
      ],
      "option_a": "অফিস খরচ",
      "option_b": "প্রশাসনিক",
      "option_c": "বিক্রয়",
      "option_d": "আরোপণ যোগ্য (প্রত্যক্ষ)",
      "correct": "ঘ",
      "explanation": "দরপত্রের ক্রয়মূল্য একটি আরোপণ যোগ্য (প্রত্যক্ষ) খরচ ।"
    },
    {
      "number": "24",
      "tag": "Din B 25",
      "question": "কোন ক্ষেত্রে বিপরীত দাখিলা হবে?",
      "options": [
        {
          "label": "ক",
          "text": "ব্যক্তিগত প্রয়োজনে ব্যাংক হতে উত্তোলন",
          "is_correct": false
        },
        {
          "label": "খ",
          "text": "মালিক কর্তৃক পণ্য উত্তোলন",
          "is_correct": false
        },
        {
          "label": "গ",
          "text": "ব্যক্তিগত প্রয়োজনে নগদ উত্তোলন",
          "is_correct": false
        },
        {
          "label": "ঘ",
          "text": "ব্যবসায়ের প্রয়োজনে ব্যাংক হতে উত্তোলন",
          "is_correct": true
        }
      ],
      "option_a": "ব্যক্তিগত প্রয়োজনে ব্যাংক হতে উত্তোলন",
      "option_b": "মালিক কর্তৃক পণ্য উত্তোলন",
      "option_c": "ব্যক্তিগত প্রয়োজনে নগদ উত্তোলন",
      "option_d": "ব্যবসায়ের প্রয়োজনে ব্যাংক হতে উত্তোলন",
      "correct": "ঘ",
      "explanation": "\"ব্যবসায়ের প্রয়োজনে ব্যাংক হতে উত্তোলন\" (Withdrawing cash from the bank for business use) ঘ ক্ষেত্রে বিপরীত দাখিলা (Contra Entry) হবে। ব্যাখ্যা বিপরীত দাখিলা : যখন কোনো লেনদেনের ফলে নগদান বইয়ের নগদ কলাম এবং ব্যাংক কলাম উভয়ই প্রভাবিত হয় (একটি ডেবিট এবং অন্যটি ক্রেডিট), তখন তাকে বিপরীত দাখিলা বলে। এটি শুধুমাত্র নগদান বইয়ের মধ্যেই সীমাবদ্ধ থাকে এবং খতিয়ানে স্থানান্তর করার প্রয়োজন হয় না (সাধারণত C বা কন্ট্রা চিহ্ন দেওয়া হয়)। \"ব্যবসায়ের প্রয়োজনে ব্যাংক হতে উত্তোলন\" : এই লেনদেনে প্রতিষ্ঠানের নগদ টাকা (নগদ হিসাব ডেবিট) বাড়ে এবং ব্যাংকে জমার পরিমাণ (ব্যাংক হিসাব ক্রেডিট) কমে। যেহেতু নগদান বইয়ের দুটি কলামই প্রভাবিত হয়েছে, এটি একটি বিপরীত দাখিলা।"
    },
    {
      "number": "25",
      "tag": "Din B 25",
      "question": "কোনটি বিক্রয় উপরিব্যয়?",
      "options": [
        {
          "label": "ক",
          "text": "আইন খরচ",
          "is_correct": false
        },
        {
          "label": "খ",
          "text": "শো-রুম ভাড়া",
          "is_correct": true
        },
        {
          "label": "গ",
          "text": "মনিহারি ব্যয়",
          "is_correct": false
        },
        {
          "label": "ঘ",
          "text": "অগ্নি বিমা",
          "is_correct": false
        }
      ],
      "option_a": "আইন খরচ",
      "option_b": "শো-রুম ভাড়া",
      "option_c": "মনিহারি ব্যয়",
      "option_d": "অগ্নি বিমা",
      "correct": "খ",
      "explanation": "বিক্রয় উপরিব্যয় (Selling Overhead) বলতে সেই সমস্ত খরচকে বোঝায় যা পণ্য বিক্রয়ের উদ্দেশ্যে বা বিক্রয় কার্যক্রম পরিচালনার জন্য সরাসরি করা হয়।   এই মানদণ্ড অনুযায়ী, খ শো-রুম ভাড়া হলো বিক্রয় উপরিব্যয়। কারণ পণ্য ক্রেতাদের নিকট প্রদর্শনের জন্য বা বিক্রয়ের জন্য শো-রুম ব্যবহার করা হয় এবং এর ভাড়া সরাসরি বিক্রয় কার্যক্রমের সাথে জড়িত।   অন্যান্য বিকল্পগুলো হলো: ক আইন খরচ: এটি প্রশাসনিক উপরিব্যয় (Administrative Overhead)। গ মনিহারি ব্যয়: এটিও সাধারণত প্রশাসনিক বা অফিস উপরিব্যয়। ঘ অগ্নি বিমা: এটিও প্রশাসনিক বা সাধারণ উপরিব্যয়।"
    },
    {
      "number": "26",
      "tag": "Din B 25",
      "question": "পারিবারিক বাজেট তৈরি হয়-",
      "options": [
        {
          "label": "ক",
          "text": "সম্ভাব্য আয় ও ব্যয়ের ভিত্তিতে",
          "is_correct": true
        },
        {
          "label": "খ",
          "text": "সম্ভাব্য আয়ের ভিত্তিতে",
          "is_correct": false
        },
        {
          "label": "গ",
          "text": "সম্ভাব্য ব্যয়ের ভিত্তিতে",
          "is_correct": false
        },
        {
          "label": "ঘ",
          "text": "প্রকৃত আয় ও ব্যয়ের ভিত্তিতে",
          "is_correct": false
        }
      ],
      "option_a": "সম্ভাব্য আয় ও ব্যয়ের ভিত্তিতে",
      "option_b": "সম্ভাব্য আয়ের ভিত্তিতে",
      "option_c": "সম্ভাব্য ব্যয়ের ভিত্তিতে",
      "option_d": "প্রকৃত আয় ও ব্যয়ের ভিত্তিতে",
      "correct": "ক",
      "explanation": "সঠিক উত্তর: ক. সম্ভাব্য আয় ও ব্যয়ের ভিত্তিতে ব্যাখ্যা পারিবারিক বাজেট (Family Budget) হলো একটি নির্দিষ্ট সময়ের জন্য পরিবারের সম্ভাব্য (Estimated/Expected) আয় এবং সেই আয় অনুযায়ী সম্ভাব্য (Estimated/Expected) ব্যয়ের একটি পূর্বপরিকল্পনা। বাজেট তৈরি করার সময় ভবিষ্যতে কত টাকা আয় হতে পারে (যেমন: বেতন, ভাড়া) এবং সেই আয় থেকে কোন কোন খাতে কত টাকা খরচ হতে পারে (যেমন: খাদ্য, শিক্ষা, পরিবহন) তার একটি অনুমান করা হয়। প্রকৃত আয় ও ব্যয় (Actual Income and Expenditure) সাধারণত হিসাবের সময়কাল শেষ হওয়ার পরে নির্ণয় করা হয় এবং তা বাজেট বাস্তবায়নের পর বাজেটের সাথে তুলনা করার জন্য ব্যবহৃত হয়। বাজেট তৈরি হয় সবসময় ভবিষ্যতের সম্ভাবনার ওপর ভিত্তি করে।"
    },
    {
      "number": "27",
      "tag": "Din B 25",
      "question": "নিচের কোনটি ব্যবসায়ের সামাজিক দায়বদ্ধতা?",
      "options": [
        {
          "label": "ক",
          "text": "মূলধন গঠন",
          "is_correct": false
        },
        {
          "label": "খ",
          "text": "দক্ষ শ্রমিকের বেতন প্রদান",
          "is_correct": false
        },
        {
          "label": "গ",
          "text": "মেধাবীদের বৃত্তি প্রদান",
          "is_correct": true
        },
        {
          "label": "ঘ",
          "text": "পরিশ্রমী ব্যক্তিকে সম্মান প্রদান",
          "is_correct": false
        }
      ],
      "option_a": "মূলধন গঠন",
      "option_b": "দক্ষ শ্রমিকের বেতন প্রদান",
      "option_c": "মেধাবীদের বৃত্তি প্রদান",
      "option_d": "পরিশ্রমী ব্যক্তিকে সম্মান প্রদান",
      "correct": "গ",
      "explanation": "ব্যবসায়ের সামাজিক দায়বদ্ধতা (Corporate Social Responsibility) হলো এমন কাজ যা সমাজের কল্যাণে করা হয়। দেওয়া অপশনগুলোর মধ্যে মেধাবীদের বৃত্তি প্রদান সামাজিক দায়বদ্ধতার মধ্যে পড়ে। ✔ সঠিক উত্তর: গ. মেধাবীদের বৃত্তি প্রদান"
    },
    {
      "number": "28",
      "tag": "Din B 25",
      "question": "মুনাফাভোগী প্রতিষ্ঠান কোনটি?",
      "options": [
        {
          "label": "ক",
          "text": "বিজ্ঞাপনী সংস্থা",
          "is_correct": true
        },
        {
          "label": "খ",
          "text": "কলেজ",
          "is_correct": false
        },
        {
          "label": "গ",
          "text": "দাতব্য চিকিৎসালয়",
          "is_correct": false
        },
        {
          "label": "ঘ",
          "text": "সামাজিক সংস্থা",
          "is_correct": false
        }
      ],
      "option_a": "বিজ্ঞাপনী সংস্থা",
      "option_b": "কলেজ",
      "option_c": "দাতব্য চিকিৎসালয়",
      "option_d": "সামাজিক সংস্থা",
      "correct": "ক",
      "explanation": "মুনাফাভোগী প্রতিষ্ঠান (Profit-making organization) বলতে সেইসব প্রতিষ্ঠানকে বোঝায় जिनका মূল উদ্দেশ্য হলো পণ্য বা পরিষেবা বিক্রি করে লাভ করা। প্রদত্ত বিকল্পগুলোর মধ্যে: ক বিজ্ঞাপনী সংস্থা: এটি বিজ্ঞাপন সংক্রান্ত পরিষেবা প্রদান করে এবং এর প্রধান লক্ষ্য মুনাফা অর্জন করা। খ কলেজ: এটি একটি শিক্ষাপ্রতিষ্ঠান, যার প্রাথমিক উদ্দেশ্য শিক্ষা প্রদান করা, মুনাফা অর্জন নয় (যদিও কিছু বেসরকারি কলেজের আয়ের উৎস টিউশন ফি)। গ দাতব্য চিকিৎসালয়: এটি সাধারণত বিনামূল্যে বা নামমাত্র মূল্যে চিকিৎসা পরিষেবা দেয়, এর উদ্দেশ্য জনসেবা, মুনাফা নয়। ঘ সামাজিক সংস্থা: এটি সমাজসেবামূলক কাজ করে এবং এর উদ্দেশ্য মুনাফা অর্জন নয়। সুতরাং, একমাত্র বিজ্ঞাপনী সংস্থা হলো একটি স্পষ্ট মুনাফাভোগী প্রতিষ্ঠান। সঠিক উত্তর: ক বিজ্ঞাপনী সংস্থা"
    },
    {
      "number": "29",
      "tag": "Din B 25",
      "question": "ক্রেডিট নোট ব্যবহৃত হয়-",
      "options": [
        {
          "label": "ক",
          "text": "ধারে বিক্রীত পণ্য ফেরত আসলে",
          "is_correct": true
        },
        {
          "label": "খ",
          "text": "ক্রেডিট নোট ব্যবহৃত হয়। ধারে বিক্রীত পণ্য ফেরত আসলে",
          "is_correct": false
        },
        {
          "label": "গ",
          "text": "নগদে ক্রয়কৃত পণ্য ফেরত দিলে",
          "is_correct": false
        },
        {
          "label": "ঘ",
          "text": "নগদে বিক্রীত পণ্য ফেরত আসলে",
          "is_correct": false
        }
      ],
      "option_a": "ধারে বিক্রীত পণ্য ফেরত আসলে",
      "option_b": "ক্রেডিট নোট ব্যবহৃত হয়। ধারে বিক্রীত পণ্য ফেরত আসলে",
      "option_c": "নগদে ক্রয়কৃত পণ্য ফেরত দিলে",
      "option_d": "নগদে বিক্রীত পণ্য ফেরত আসলে",
      "correct": "ক",
      "explanation": "ক্রেডিট নোট ব্যবহৃত হয় ক ধারে বিক্রীত পণ্য ফেরত আসলে । Explanation ক্রেডিট নোট (Credit Note) : যখন কোনো ক্রেতা ধারে কেনা পণ্য বিক্রেতার কাছে ফেরত দেন, তখন বিক্রেতা ক্রেতাকে একটি ক্রেডিট নোট ইস্যু করেন। এই নোটটি প্রমাণ করে যে ক্রেতার হিসাবে নির্দিষ্ট পরিমাণ টাকা জমা (ক্রেডিট) করা হয়েছে, অর্থাৎ ক্রেতার দেনা কমে গেছে। ডেবিট নোট (Debit Note) : যখন কোনো ক্রেতা ধারে কেনা পণ্য বিক্রেতার কাছে ফেরত দেন (অর্থাৎ ক্রেতার দৃষ্টিকোণ থেকে), তখন ক্রেতা বিক্রেতাকে একটি ডেবিট নোট পাঠাতে পারেন। তবে সাধারণত বিক্রেতাই ক্রেডিট নোট ইস্যু করেন। অন্যান্য অপশনগুলো ভুল কারণ: গ ও ঘ (নগদে ক্রয়/বিক্রয় ফেরত) : নগদ লেনদেনের ক্ষেত্রে সাধারণত ক্যাশ মেমো বা রসিদ ব্যবহার করা হয় এবং ফেরত দেওয়ার সময় টাকা সরাসরি ফেরত দেওয়া হয়, ক্রেডিট নোটের প্রয়োজন হয় না।"
    },
    {
      "number": "30",
      "tag": "Din B 25",
      "question": "বাহ্যিক লেনদেনে অর্থনৈতিক ঘটনা কয়টি পক্ষকে প্রভাবিত করে?",
      "options": [
        {
          "label": "ক",
          "text": "১টি",
          "is_correct": false
        },
        {
          "label": "খ",
          "text": "২টি",
          "is_correct": true
        },
        {
          "label": "গ",
          "text": "৩টি",
          "is_correct": false
        },
        {
          "label": "ঘ",
          "text": "৪টি",
          "is_correct": false
        }
      ],
      "option_a": "১টি",
      "option_b": "২টি",
      "option_c": "৩টি",
      "option_d": "৪টি",
      "correct": "খ",
      "explanation": "বাহ্যিক লেনদেনে অর্থনৈতিক ঘটনা খ ২টি পক্ষকে প্রভাবিত করে। হিসাববিজ্ঞানের দ্বৈতসত্তা নীতি (Duality Concept) অনুযায়ী, প্রতিটি লেনদেনের দুটি পক্ষ থাকে: একটি পক্ষ সুবিধা গ্রহণ করে (ডেবিট), এবং অন্য পক্ষ সুবিধা প্রদান করে (ক্রেডিট)। এই দুটি পক্ষের মধ্যে আদান-প্রদান সম্পন্ন হয়।"
    }
  ]
}